dbt_native_artifacts_parser/__init__.py
dbt_native_artifacts_parser-0.1.1.dist-info/METADATA
dbt_native_artifacts_parser-0.1.1.dist-info/WHEEL
dbt_native_artifacts_parser-0.1.1.dist-info/licenses/LICENSE
dbt_native_artifacts_parser-0.1.1.dist-info/RECORD
