Metadata-Version: 2.3
Name: dbt-native-artifacts-parser
Version: 0.1.1
Summary: An artifact parser for dbt using dbt-core's built-in classes
Project-URL: Repository, https://github.com/sdebruyn/dbt-native-artifacts-parser
Author-email: Sam Debruyn <pypi.sam@debruyn.dev>
License: MIT
License-File: LICENSE
Keywords: artifacts,dbt,dbt-core,parser
Requires-Python: >=3.8
Requires-Dist: dbt-core>=1.8.7
